somfy_rts_hub-1.1.dist-info/licenses/LICENSE
somfyrtshub/__init__.py
somfyrtshub/const.py
somfyrtshub/cover.py
somfyrtshub/errors.py
somfyrtshub/hub.py
somfy_rts_hub-1.1.dist-info/METADATA
somfy_rts_hub-1.1.dist-info/WHEEL
somfy_rts_hub-1.1.dist-info/top_level.txt
somfy_rts_hub-1.1.dist-info/RECORD
