Metadata-Version: 2.4
Name: somfy-rts-hub
Version: 1.1
Summary: A small package to talk to somfy-rts-esp devices.
Author-email: Lukas Hirsch <lukas.stag@gmail.com>
License-Expression: MIT
Project-URL: Homepage, https://github.com/LukasHirsch99/somfy-rts-hub
Project-URL: Issues, https://github.com/LukasHirsch99/somfy-rts-hub/issues
Classifier: Programming Language :: Python :: 3
Classifier: Operating System :: OS Independent
License-File: LICENSE
Dynamic: license-file
